Workbook

Sheet Planilha1
C11: CONFIGURAÇÕES
C13: Salário | E13: 2000
C14: Rendimento carteira | E14: 0.006
C15: Sugestão de investimento | E15: =$E$13*30% -> 600
C17: INVESTIMENTO MENSAL
C18: Quanto invertir por mês? | E18: 200
C19: Por quantos anos? | E19: 5
C20: Taxa de rendimento mensal? | E20: 0.01079
C21: Patrimônio acumulado? | E21: =FV(E20,(E19*12),E18)*-1 -> 16755.383
C22: Dividendos Mensais | E22: =E21*$E$14 -> 100.5323
C24: ANOS | D24: CENÁRIOS | F24: DIVIDENDO
C25: 2 | D25: Quanto em 2 anos? | E25: =FV($E$20,$C25*12,$E$18)*-1 -> 5445.5255 | F25: =$E25*$E$14 -> 32.673153
C26: 5 | D26: Quanto em 5 anos? | E26: =FV($E$20,$C26*12,$E$18)*-1 -> 16755.383 | F26: =$E26*$E$14 -> 100.5323
C27: 10 | D27: Quanto em 10 anos? | E27: =FV($E$20,$C27*12,$E$18)*-1 -> 48656.843 | F27: =$E27*$E$14 -> 291.94106
C28: 20 | D28: Quanto em 20 anos? | E28: =FV($E$20,$C28*12,$E$18)*-1 -> 225039.68 | F28: =$E28*$E$14 -> 1350.2381
C29: 30 | D29: Quanto em 30 anos? | E29: =FV($E$20,$C29*12,$E$18)*-1 -> 864433.93 | F29: =$E29*$E$14 -> 5186.6036
D31: Perfil | E31: Agressivo
D32: Valor a ser investido por mês | E32: =E18 -> 200
C35: TIPO DE FII | E35: PERCENTURAL SUGERIDO | F35: VALORES
C36: PAPEL | E36: =VLOOKUP($E$31&"-"&$C36,Planilha2!A1:D23,4,FALSE) -> 0.5 | F36: =$E$32*$E36 -> 100
C37: TIJOLO | E37: =VLOOKUP($E$31&"-"&$C37,Planilha2!A2:D24,4,FALSE) -> 0.1 | F37: =$E$32*$E37 -> 20
C38: HÍBRIDOS | E38: =VLOOKUP($E$31&"-"&$C38,Planilha2!A3:D25,4,FALSE) -> 0.05 | F38: =$E$32*$E38 -> 10
C39: FOFs | E39: =VLOOKUP($E$31&"-"&$C39,Planilha2!A4:D26,4,FALSE) -> 0.05 | F39: =$E$32*$E39 -> 10
C40: DESENVOLVIMENTO | E40: =VLOOKUP($E$31&"-"&$C40,Planilha2!A5:D27,4,FALSE) -> 0.2 | F40: =$E$32*$E40 -> 40
C41: HOTELARIAS | E41: =VLOOKUP($E$31&"-"&$C41,Planilha2!A6:D28,4,FALSE) -> 0.1 | F41: =$E$32*$E41 -> 20
F42: =SUM(F36:F41) -> 200

Sheet Planilha2
A1: CHAVE | B1: PERFIL | C1: TIPO DE FII | D1: %
A2: =$B2&"-"&$C2 -> Conservador-PAPEL | B2: Conservador | C2: PAPEL | D2: 0.3
A3: =$B3&"-"&$C3 -> Conservador- TIJOLO | B3: Conservador | C3: TIJOLO | D3: 0.5
A4: =$B4&"-"&$C4 -> Conservador- HÍBRIDOS | B4: Conservador | C4: HÍBRIDOS | D4: 0.1
A5: =$B5&"-"&$C5 -> Conservador- FOFs | B5: Conservador | C5: FOFs | D5: 0.1
A6: =$B6&"-"&$C6 -> Conservador- DESENVOLVIMENTO | B6: Conservador | C6: DESENVOLVIMENTO | D6: 0
A7: =$B7&"-"&$C7 -> Conservador- HOTELARIAS | B7: Conservador | C7: HOTELARIAS | D7: 0
A9: CHAVE | B9: PERFIL | C9: TIPO DE FII | D9: %
A10: =$B10&"-"&$C10 -> Moderado-PAPEL | B10: Moderado | C10: PAPEL | D10: 0.32
A11: =$B11&"-"&$C11 -> Moderado- TIJOLO | B11: Moderado | C11: TIJOLO | D11: 0.35
A12: =$B12&"-"&$C12 -> Moderado- HÍBRIDOS | B12: Moderado | C12: HÍBRIDOS | D12: 0.08
A13: =$B13&"-"&$C13 -> Moderado- FOFs | B13: Moderado | C13: FOFs | D13: 0.05
A14: =$B14&"-"&$C14 -> Moderado- DESENVOLVIMENTO | B14: Moderado | C14: DESENVOLVIMENTO | D14: 0.1
A15: =$B15&"-"&$C15 -> Moderado- HOTELARIAS | B15: Moderado | C15: HOTELARIAS | D15: 0.1
E16: 2
A17: CHAVE | B17: PERFIL | C17: TIPO DE FII | D17: %
A18: =$B18&"-"&$C18 -> Agressivo-PAPEL | B18: Agressivo | C18: PAPEL | D18: 0.5
A19: =$B19&"-"&$C19 -> Agressivo- TIJOLO | B19: Agressivo | C19: TIJOLO | D19: 0.1
A20: =$B20&"-"&$C20 -> Agressivo- HÍBRIDOS | B20: Agressivo | C20: HÍBRIDOS | D20: 0.05
A21: =$B21&"-"&$C21 -> Agressivo- FOFs | B21: Agressivo | C21: FOFs | D21: 0.05
A22: =$B22&"-"&$C22 -> Agressivo- DESENVOLVIMENTO | B22: Agressivo | C22: DESENVOLVIMENTO | D22: 0.2
A23: =$B23&"-"&$C23 -> Agressivo- HOTELARIAS | B23: Agressivo | C23: HOTELARIAS | D23: 0.1
